karrio/mappers/aramex/__init__.py
karrio/mappers/aramex/mapper.py
karrio/mappers/aramex/proxy.py
karrio/mappers/aramex/settings.py
karrio/plugins/aramex/__init__.py
karrio/providers/aramex/__init__.py
karrio/providers/aramex/error.py
karrio/providers/aramex/tracking.py
karrio/providers/aramex/units.py
karrio/providers/aramex/utils.py
karrio/schemas/aramex/__init__.py
karrio/schemas/aramex/array_of_string.py
karrio/schemas/aramex/datatypes.py
karrio/schemas/aramex/location.py
karrio/schemas/aramex/rates.py
karrio/schemas/aramex/shipping.py
karrio/schemas/aramex/tracking.py
karrio_aramex-2026.1.4.dist-info/METADATA
karrio_aramex-2026.1.4.dist-info/WHEEL
karrio_aramex-2026.1.4.dist-info/entry_points.txt
karrio_aramex-2026.1.4.dist-info/top_level.txt
karrio_aramex-2026.1.4.dist-info/RECORD
